djangofp/cli.py
djangofp/signatures.json
djangofp-0.2.1.dist-info/licenses/LICENSE
djangofp-0.2.1.dist-info/METADATA
djangofp-0.2.1.dist-info/WHEEL
djangofp-0.2.1.dist-info/entry_points.txt
djangofp-0.2.1.dist-info/top_level.txt
djangofp-0.2.1.dist-info/RECORD
