Metadata-Version: 2.4
Name: djangofp
Version: 0.2.1
Summary: Simple Django static-asset version probe
Requires-Python: >=3.13
License-File: LICENSE
Requires-Dist: bs4>=0.0.2
Requires-Dist: requests>=2.32.5
Provides-Extra: dev
Requires-Dist: build>=1.3.0; extra == "dev"
Requires-Dist: twine>=6.2.0; extra == "dev"
Dynamic: license-file
